Metadata-Version: 2.1
Name: mycarehub-backend-django
Version: 0.0.1
Summary: Field Reporting Database for the mycarehub care delivery projects.
Home-page: https://github.com/savannahghi/mycarehub-backend
Author: SIL
Author-email: developers@savannahinformatics.com
License: MIT License
Platform: UNKNOWN
Classifier: Environment :: Web Environment
Classifier: Framework :: Django
Classifier: Intended Audience :: Developers
Classifier: License :: OSI Approved :: MIT License
Classifier: Operating System :: OS Independent
Classifier: Programming Language :: Python
Classifier: Programming Language :: Python :: 3
Classifier: Programming Language :: Python :: 3 :: Only
Classifier: Programming Language :: Python :: 3.8
Classifier: Programming Language :: Python :: 3.9
Classifier: Topic :: Internet :: WWW/HTTP
Classifier: Topic :: Internet :: WWW/HTTP :: Dynamic Content
License-File: LICENSE
Requires-Dist: psycopg2-binary (~=2.9.1)
Requires-Dist: Fraction (~=2.1.1)
Requires-Dist: Pillow (~=8.4.0)
Requires-Dist: argon2-cffi (~=21.1.0)
Requires-Dist: coveralls (~=3.3.0)
Requires-Dist: django-extensions (~=3.1.3)
Requires-Dist: django-allauth (~=0.45.0)
Requires-Dist: django-anymail[mailgun] (~=8.4)
Requires-Dist: django-compressor (~=2.4.1)
Requires-Dist: django-cors-headers (~=3.10.0)
Requires-Dist: django-crispy-forms (~=1.13.0)
Requires-Dist: django-environ (~=0.8.1)
Requires-Dist: django-filter (<3.0,>=2.2)
Requires-Dist: django-mjml[requests] (~=0.11.0)
Requires-Dist: django-taggit (~=1.5.1)
Requires-Dist: django-modelcluster (~=5.2)
Requires-Dist: django-model-utils (~=4.2.0)
Requires-Dist: django-oauth-toolkit (~=1.5.0)
Requires-Dist: django-phonenumber-field (~=5.2.0)
Requires-Dist: django-storages[google] (~=1.12.3)
Requires-Dist: djangorestframework-datatables (~=0.6.0)
Requires-Dist: djangorestframework (~=3.12.4)
Requires-Dist: django-rest-framework-braces (~=0.3.4)
Requires-Dist: drf-generators (~=0.5.0)
Requires-Dist: django (~=3.2.6)
Requires-Dist: google-api-core (~=2.2.2)
Requires-Dist: google-api-python-client (~=2.29.0)
Requires-Dist: google-auth (~=2.3.3)
Requires-Dist: google-cloud-secret-manager (~=2.7.0)
Requires-Dist: google-cloud-storage (~=1.42.3)
Requires-Dist: gcloud (~=0.18.3)
Requires-Dist: graphene-django (~=2.15.0)
Requires-Dist: openpyxl (~=3.0.7)
Requires-Dist: phonenumbers (~=8.12.29)
Requires-Dist: python-slugify (~=5.0.2)
Requires-Dist: pytz (~=2021.1)
Requires-Dist: rcssmin (~=1.0.6)
Requires-Dist: requests (~=2.26.0)
Requires-Dist: uvicorn[standard] (~=0.15.0)
Requires-Dist: whitenoise (~=5.3.0)
Requires-Dist: wagtail (~=2.15.1)
Requires-Dist: Wand (~=0.6.7)
Requires-Dist: opencv-python (~=4.5.4.58)
Requires-Dist: rustface (~=0.1.0)
Requires-Dist: wagtailvideos (~=2.10.9)
Requires-Dist: wagtailmedia (~=0.8.0)
Requires-Dist: wagtail-readinglevel (~=3.5.0)
Requires-Dist: wagtailfontawesome (~=1.2.1)
Requires-Dist: wagtail-quick-create (~=1.0.7)
Requires-Dist: wagtail-automatic-redirects (~=1.1.5)
